setup.py
bin/docker-purge
docker_purge/__init__.py
docker_purge.egg-info/PKG-INFO
docker_purge.egg-info/SOURCES.txt
docker_purge.egg-info/dependency_links.txt
docker_purge.egg-info/entry_points.txt
docker_purge.egg-info/not-zip-safe
docker_purge.egg-info/requires.txt
docker_purge.egg-info/top_level.txt