Metadata-Version: 1.0
Name: docker-purge
Version: 0.1
Summary: One command to rule all purges on your docker engine.
Home-page: https://github.com/matglas/docker_purge.git
Author: Matthias Glastra
Author-email: matthias@vdmi.nl
License: MIT
Platform: UNKNOWN
